uno_mcp_stdio/__init__.py
uno_mcp_stdio/config.py
uno_mcp_stdio/main.py
uno_mcp_stdio/stdio_server.py
uno_mcp_stdio/auth/__init__.py
uno_mcp_stdio/auth/callback_server.py
uno_mcp_stdio/auth/token_manager.py
uno_mcp_stdio/gateway/__init__.py
uno_mcp_stdio/gateway/proxy.py
uno_mcp_stdio-0.2.0.dist-info/METADATA
uno_mcp_stdio-0.2.0.dist-info/WHEEL
uno_mcp_stdio-0.2.0.dist-info/entry_points.txt
uno_mcp_stdio-0.2.0.dist-info/RECORD
