Metadata-Version: 2.4
Name: uno-mcp-stdio
Version: 0.2.0
Summary: Uno MCP Stdio Client - Local stdio proxy for Uno MCP Gateway with OAuth authentication
Project-URL: Homepage, https://github.com/agentrix-ai/uno-mcp-stdio
Project-URL: Repository, https://github.com/agentrix-ai/uno-mcp-stdio
Project-URL: Documentation, https://github.com/agentrix-ai/uno-mcp-stdio#readme
Project-URL: Issues, https://github.com/agentrix-ai/uno-mcp-stdio/issues
Author-email: xray918 <xray918@example.com>
License: MIT
Keywords: agent,ai,mcp,oauth,proxy,stdio
Classifier: Development Status :: 4 - Beta
Classifier: Intended Audience :: Developers
Classifier: License :: OSI Approved :: MIT License
Classifier: Programming Language :: Python :: 3
Classifier: Programming Language :: Python :: 3.11
Classifier: Programming Language :: Python :: 3.12
Classifier: Topic :: Scientific/Engineering :: Artificial Intelligence
Classifier: Topic :: Software Development :: Libraries :: Python Modules
Requires-Python: >=3.11
Requires-Dist: aiofiles>=23.2.0
Requires-Dist: httpx>=0.27.0
Requires-Dist: mcp>=1.0.0
Requires-Dist: pydantic-settings>=2.1.0
Requires-Dist: pydantic>=2.5.0
Provides-Extra: dev
Requires-Dist: black>=24.0.0; extra == 'dev'
Requires-Dist: isort>=5.13.0; extra == 'dev'
Requires-Dist: mypy>=1.8.0; extra == 'dev'
Requires-Dist: pytest-asyncio>=0.23.0; extra == 'dev'
Requires-Dist: pytest>=7.4.0; extra == 'dev'
